pypyterminal/__init__.py
pypyterminal/commands.py
pypyterminal/utils.py
pypyterminal-0.0.1.dist-info/METADATA
pypyterminal-0.0.1.dist-info/WHEEL
pypyterminal-0.0.1.dist-info/top_level.txt
pypyterminal-0.0.1.dist-info/RECORD
