Metadata-Version: 2.1
Name: pypyterminal
Version: 0.0.1
Summary: A library to automate and shorten terminal commands for Python development on Ubuntu
Author: Abdullah
Author-email: abdullahashik2001@gmail.com
Classifier: Programming Language :: Python :: 3
Classifier: License :: OSI Approved :: MIT License
Classifier: Operating System :: OS Independent
Requires-Python: >=3.6
Requires-Dist: click
Requires-Dist: virtualenv
Requires-Dist: jupyter
